{
  "phase": 4,
  "status": "pass",
  "timestamp": "2026-04-14T12:08:39Z",
  "commit": "ee2c7b5",
  "failure_reason": "",
  "regression_gate": {
    "phase3": "pass",
    "log": "reports/phase4_phase3_gate.log"
  },
  "swiftpm": {
    "phase4_failures": 0,
    "phase4_pass_markers": 214,
    "phase4_log": "reports/phase4_swiftpm_phase4.log",
    "full_suite_failures": 0,
    "full_suite_pass_markers": 2555,
    "full_suite_log": "reports/phase4_swiftpm_full.log"
  },
  "xcodebuild": {
    "macOS": "pass",
    "iPhone": "pass",
    "iPad": "pass",
    "coverage": "present",
    "coverage_report": "reports/phase4_coverage.txt",
    "coverage_log": "reports/phase4_coverage_macos.log",
    "result_bundles": {
      "macOS": "/tmp/QuartzPhase4-macOS.xcresult",
      "macOSCoverage": "/tmp/QuartzPhase4-macOS-coverage.xcresult",
      "iPhone": "/tmp/QuartzPhase4-iPhone.xcresult",
      "iPad": "/tmp/QuartzPhase4-iPad.xcresult"
    }
  },
  "ui_matrix": {
    "passed": 3,
    "failed": 0,
    "skipped": 0,
    "logs": [
      "reports/ui_matrix_macos.log",
      "reports/ui_matrix_ios.log",
      "reports/ui_matrix_ipados.log"
    ]
  },
  "self_healing": {
    "ran": false,
    "log": "reports/phase4_heal_log.txt",
    "artifacts": ""
  }
}
